django_google_spanner-4.0.2.dist-info/licenses/LICENSE
django_spanner/__init__.py
django_spanner/_opentelemetry_tracing.py
django_spanner/base.py
django_spanner/client.py
django_spanner/compiler.py
django_spanner/creation.py
django_spanner/features.py
django_spanner/functions.py
django_spanner/introspection.py
django_spanner/lookups.py
django_spanner/operations.py
django_spanner/schema.py
django_spanner/utils.py
django_spanner/version.py
django_google_spanner-4.0.2.dist-info/METADATA
django_google_spanner-4.0.2.dist-info/WHEEL
django_google_spanner-4.0.2.dist-info/top_level.txt
django_google_spanner-4.0.2.dist-info/RECORD
