Metadata-Version: 2.4
Name: django-google-spanner
Version: 4.0.2
Summary: Bridge to enable using Django with Spanner.
Home-page: https://github.com/googleapis/python-spanner-django
Author: Google LLC
Author-email: googleapis-packages@google.com
License: BSD
Classifier: Development Status :: 5 - Production/Stable
Classifier: Environment :: Web Environment
Classifier: Intended Audience :: Developers
Classifier: License :: OSI Approved :: BSD License
Classifier: Operating System :: OS Independent
Classifier: Programming Language :: Python :: 3
Classifier: Programming Language :: Python :: 3.8
Classifier: Programming Language :: Python :: 3.9
Classifier: Programming Language :: Python :: 3.10
Classifier: Topic :: Utilities
Classifier: Framework :: Django
Classifier: Framework :: Django :: 3.2
Classifier: Framework :: Django :: 4.2
Requires-Python: >=3.8
License-File: LICENSE
Requires-Dist: sqlparse>=0.3.0
Requires-Dist: google-cloud-spanner>=3.13.0
Provides-Extra: tracing
Requires-Dist: opentelemetry-api>=1.1.0; extra == "tracing"
Requires-Dist: opentelemetry-sdk>=1.1.0; extra == "tracing"
Requires-Dist: opentelemetry-instrumentation>=0.20b0; extra == "tracing"
Dynamic: author
Dynamic: author-email
Dynamic: classifier
Dynamic: description
Dynamic: home-page
Dynamic: license
Dynamic: license-file
Dynamic: provides-extra
Dynamic: requires-dist
Dynamic: requires-python
Dynamic: summary
